keypractice/__init__.py
keypractice/__main__.py
keypractice/analytics.py
keypractice/core.py
keypractice/data/analytics.json
keypractice/exercises/home_row.yaml
keypractice/exercises/special_characters.yaml
keypractice-0.1.11.dist-info/METADATA
keypractice-0.1.11.dist-info/WHEEL
keypractice-0.1.11.dist-info/entry_points.txt
keypractice-0.1.11.dist-info/top_level.txt
keypractice-0.1.11.dist-info/RECORD
