Metadata-Version: 2.4
Name: keypractice
Version: 0.1.11
Summary: A slim, cross-platform terminal-based typing trainer with YAML-based exercises and analytics.
Author: Stephen
Requires-Python: >=3.7
Requires-Dist: PyYAML>=6.0
Dynamic: author
Dynamic: description
Dynamic: description-content-type
Dynamic: requires-dist
Dynamic: requires-python
Dynamic: summary
